cuda_installer.py
ai_gpu_pkgs-0.1.0.dist-info/licenses/LICENSE
ai_gpu_pkgs-0.1.0.dist-info/METADATA
ai_gpu_pkgs-0.1.0.dist-info/WHEEL
ai_gpu_pkgs-0.1.0.dist-info/entry_points.txt
ai_gpu_pkgs-0.1.0.dist-info/top_level.txt
ai_gpu_pkgs-0.1.0.dist-info/RECORD
