Metadata-Version: 2.4
Name: ai-gpu-pkgs
Version: 0.1.0
Summary: Automatic GPU package installer for AI/ML development
Author-email: mrbeandev <mrbeandev@gmail.com>
License: MIT
Project-URL: Homepage, https://github.com/mrbeandev/cuda-auto-installer
Project-URL: Repository, https://github.com/mrbeandev/cuda-auto-installer
Project-URL: Issues, https://github.com/mrbeandev/cuda-auto-installer/issues
Keywords: ai,gpu,cuda,pytorch,model-context-protocol
Classifier: Development Status :: 3 - Alpha
Classifier: Intended Audience :: Developers
Classifier: License :: OSI Approved :: MIT License
Classifier: Programming Language :: Python :: 3
Classifier: Programming Language :: Python :: 3.8
Classifier: Programming Language :: Python :: 3.9
Classifier: Programming Language :: Python :: 3.10
Classifier: Programming Language :: Python :: 3.11
Classifier: Topic :: Scientific/Engineering :: Artificial Intelligence
Requires-Python: >=3.8
License-File: LICENSE
Requires-Dist: pynvml>=11.0.0
Dynamic: license-file
